arcos_gui/__init__.py
arcos_gui/__main__.py
arcos_gui/_helper_functions.py
arcos_gui/_main_widget.py
arcos_gui/napari.yaml
arcos_gui/_icons/Dual Ring-1s-200px.gif
arcos_gui/_icons/enlarge_window.png
arcos_gui/_icons/folder-open-line.svg
arcos_gui/_ui/ARCOS_widget.ui
arcos_gui/_ui/Input_data.ui
arcos_gui/_ui/Layer_properties.ui
arcos_gui/_ui/data_plot_dialog.ui
arcos_gui/_ui/export_widget.ui
arcos_gui/_ui/filter_data.ui
arcos_gui/_ui/main_widget.ui
arcos_gui/_ui/plot_dialog.ui
arcos_gui/_ui/plot_widget.ui
arcos_gui/layerutils/__init__.py
arcos_gui/layerutils/_layer_data_tuple.py
arcos_gui/layerutils/_layer_maker.py
arcos_gui/processing/__init__.py
arcos_gui/processing/_arcos_wrapper.py
arcos_gui/processing/_data_storage.py
arcos_gui/processing/_preprocessing_utils.py
arcos_gui/sample_data/__init__.py
arcos_gui/sample_data/_sample_data.py
arcos_gui/sample_data/arcos_data.csv
arcos_gui/sample_data/arcos_data_2.csv
arcos_gui/tools/__init__.py
arcos_gui/tools/_config.py
arcos_gui/tools/_image_sequence_export.py
arcos_gui/tools/_plots.py
arcos_gui/tools/_shape_functions.py
arcos_gui/tools/_ui_util_func.py
arcos_gui/widgets/__init__.py
arcos_gui/widgets/_arcos_widget.py
arcos_gui/widgets/_bottom_bar_widget.py
arcos_gui/widgets/_dialog_widgets.py
arcos_gui/widgets/_exporting_widget.py
arcos_gui/widgets/_filter_widget.py
arcos_gui/widgets/_input_data_widget.py
arcos_gui/widgets/_plot_widgets.py
arcos_gui/widgets/_visualization_settings_widget.py
arcos_gui-0.1.5.dist-info/licenses/LICENSE
arcos_gui-0.1.5.dist-info/METADATA
arcos_gui-0.1.5.dist-info/WHEEL
arcos_gui-0.1.5.dist-info/entry_points.txt
arcos_gui-0.1.5.dist-info/top_level.txt
arcos_gui-0.1.5.dist-info/RECORD
