Metadata-Version: 2.4
Name: arcos-gui
Version: 0.1.5
Summary: A napari plugin to detect and visualize collective signaling events
Home-page: https://github.com/bgraedel/arcos-gui
Author: Benjamin Grädel
Author-email: benjamin.graedel@unibe.ch
License: BSD-3-Clause
Project-URL: Bug Tracker, https://github.com/bgraedel/arcos-gui/issues
Project-URL: Documentation, https://pertzlab.github.io/arcos-gui/
Project-URL: Source Code, https://github.com/bgraedel/arcos-gui
Project-URL: User Support, https://github.com/bgraedel/arcos-gui/issues
Classifier: Development Status :: 4 - Beta
Classifier: Framework :: napari
Classifier: Intended Audience :: Developers
Classifier: License :: OSI Approved :: BSD License
Classifier: Operating System :: OS Independent
Classifier: Programming Language :: Python
Classifier: Programming Language :: Python :: 3
Classifier: Programming Language :: Python :: 3 :: Only
Classifier: Programming Language :: Python :: 3.9
Classifier: Programming Language :: Python :: 3.10
Classifier: Programming Language :: Python :: 3.11
Classifier: Programming Language :: Python :: 3.12
Classifier: Topic :: Software Development :: Testing
Requires-Python: >=3.9
License-File: LICENSE
Requires-Dist: arcos4py>=0.3.1
Requires-Dist: matplotlib>=3.3.4
Requires-Dist: napari>=0.4.14
Requires-Dist: numpy>=1.22.2; python_version >= "3.10"
Requires-Dist: numpy<2,>=1.22.2; python_version < "3.10"
Requires-Dist: pandas>=1.3.5
Requires-Dist: pyarrow>=11.0.0
Requires-Dist: scikit-image>=0.20.0; python_version < "3.12"
Requires-Dist: scikit-image>=0.22.0; python_version >= "3.12"
Requires-Dist: scipy>=1.7.3
Requires-Dist: napari-timestamper
Provides-Extra: doc
Requires-Dist: mkdocs; extra == "doc"
Requires-Dist: mkdocs-include-markdown-plugin; extra == "doc"
Requires-Dist: mkdocs-material; extra == "doc"
Requires-Dist: mkdocs-material-extensions; extra == "doc"
Provides-Extra: testing
Requires-Dist: pyqt5; extra == "testing"
Requires-Dist: pytest; extra == "testing"
Requires-Dist: pytest-mock; extra == "testing"
Requires-Dist: pytest-qt; extra == "testing"
Dynamic: license-file
